Metadata-Version: 2.4
Name: flask-fs2
Version: 0.7.33
Summary: Simple and easy file storages for Flask
Home-page: https://github.com/cgwire/flask-fs2
Author: Axel Haustant
Author-email: noirbizarre@gmail.com
Maintainer: CG Wire
Maintainer-email: support@cg-wire.com
License: MIT
Classifier: Development Status :: 5 - Production/Stable
Classifier: Programming Language :: Python
Classifier: Environment :: Web Environment
Classifier: Operating System :: OS Independent
Classifier: Intended Audience :: Developers
Classifier: Topic :: System :: Software Distribution
Classifier: Programming Language :: Python
Classifier: Programming Language :: Python :: 3.10
Classifier: Programming Language :: Python :: 3.11
Classifier: Programming Language :: Python :: 3.12
Classifier: Programming Language :: Python :: 3.13
Classifier: Programming Language :: Python :: 3.14
Classifier: Programming Language :: Python :: Implementation :: CPython
Classifier: Programming Language :: Python :: Implementation :: PyPy
Classifier: Topic :: Internet :: WWW/HTTP :: Dynamic Content
Classifier: Topic :: Software Development :: Libraries :: Python Modules
Classifier: License :: OSI Approved :: MIT License
Requires-Python: >=3.10
Requires-Dist: flask>=2.0.0
Requires-Dist: python-dateutil==2.9.0.post0
Requires-Dist: Werkzeug>=2.0.0
Requires-Dist: cryptography>=39.0.2
Provides-Extra: doc
Requires-Dist: boto3>=1.28.0; extra == "doc"
Requires-Dist: python-swiftclient>=4.4.0; extra == "doc"
Requires-Dist: python-keystoneclient>=5.2.0; extra == "doc"
Requires-Dist: pymongo>=4.5.0; extra == "doc"
Requires-Dist: sphinx==9.1.0; extra == "doc"
Requires-Dist: alabaster==1.0.0; extra == "doc"
Requires-Dist: pillow==12.1.0; extra == "doc"
Provides-Extra: test
Requires-Dist: boto3>=1.28.0; extra == "test"
Requires-Dist: pymongo>=4.5.0; extra == "test"
Requires-Dist: python-swiftclient>=4.4.0; extra == "test"
Requires-Dist: python-keystoneclient>=5.2.0; extra == "test"
Requires-Dist: pytest==9.0.2; extra == "test"
Requires-Dist: pytest-faker==2.0.0; extra == "test"
Requires-Dist: pytest-sugar==1.1.1; extra == "test"
Requires-Dist: pytest-mock==3.15.1; extra == "test"
Requires-Dist: pillow==12.1.0; extra == "test"
Requires-Dist: flask-mongoengine-3==1.1.0; extra == "test"
Provides-Extra: s3
Requires-Dist: boto3>=1.28.0; extra == "s3"
Provides-Extra: swift
Requires-Dist: python-swiftclient>=4.4.0; extra == "swift"
Requires-Dist: python-keystoneclient>=5.2.0; extra == "swift"
Provides-Extra: gridfs
Requires-Dist: pymongo>=4.5.0; extra == "gridfs"
Provides-Extra: all
Requires-Dist: boto3>=1.28.0; extra == "all"
Requires-Dist: python-swiftclient>=4.4.0; extra == "all"
Requires-Dist: python-keystoneclient>=5.2.0; extra == "all"
Requires-Dist: pymongo>=4.5.0; extra == "all"
Provides-Extra: qa
Requires-Dist: boto3>=1.28.0; extra == "qa"
Requires-Dist: pymongo>=4.5.0; extra == "qa"
Requires-Dist: python-swiftclient>=4.4.0; extra == "qa"
Requires-Dist: python-keystoneclient>=5.2.0; extra == "qa"
Requires-Dist: pytest==9.0.2; extra == "qa"
Requires-Dist: pytest-faker==2.0.0; extra == "qa"
Requires-Dist: pytest-sugar==1.1.1; extra == "qa"
Requires-Dist: pytest-mock==3.15.1; extra == "qa"
Requires-Dist: pillow==12.1.0; extra == "qa"
Requires-Dist: flask-mongoengine-3==1.1.0; extra == "qa"
Provides-Extra: ci
Requires-Dist: invoke==2.2.0; extra == "ci"
Requires-Dist: coveralls==4.0.2; extra == "ci"
Requires-Dist: pytest-flask==1.3.0; extra == "ci"
Requires-Dist: boto3>=1.28.0; extra == "ci"
Requires-Dist: pymongo>=4.5.0; extra == "ci"
Requires-Dist: python-swiftclient>=4.4.0; extra == "ci"
Requires-Dist: python-keystoneclient>=5.2.0; extra == "ci"
Requires-Dist: pytest==9.0.2; extra == "ci"
Requires-Dist: pytest-faker==2.0.0; extra == "ci"
Requires-Dist: pytest-sugar==1.1.1; extra == "ci"
Requires-Dist: pytest-mock==3.15.1; extra == "ci"
Requires-Dist: pillow==12.1.0; extra == "ci"
Requires-Dist: flask-mongoengine-3==1.1.0; extra == "ci"
Requires-Dist: flake8==7.3.0; extra == "ci"
Requires-Dist: pytest-cov==7.0.0; extra == "ci"
Provides-Extra: dev
Requires-Dist: invoke==2.2.0; extra == "dev"
Requires-Dist: tox==4.34.1; extra == "dev"
Requires-Dist: black==25.12.0; extra == "dev"
Requires-Dist: pre-commit==4.5.1; extra == "dev"
Requires-Dist: autoflake==2.3.1; extra == "dev"
Requires-Dist: setuptools; extra == "dev"
Requires-Dist: boto3>=1.28.0; extra == "dev"
Requires-Dist: pymongo>=4.5.0; extra == "dev"
Requires-Dist: python-swiftclient>=4.4.0; extra == "dev"
Requires-Dist: python-keystoneclient>=5.2.0; extra == "dev"
Requires-Dist: pytest==9.0.2; extra == "dev"
Requires-Dist: pytest-faker==2.0.0; extra == "dev"
Requires-Dist: pytest-sugar==1.1.1; extra == "dev"
Requires-Dist: pytest-mock==3.15.1; extra == "dev"
Requires-Dist: pillow==12.1.0; extra == "dev"
Requires-Dist: flask-mongoengine-3==1.1.0; extra == "dev"
Requires-Dist: boto3>=1.28.0; extra == "dev"
Requires-Dist: python-swiftclient>=4.4.0; extra == "dev"
Requires-Dist: python-keystoneclient>=5.2.0; extra == "dev"
Requires-Dist: pymongo>=4.5.0; extra == "dev"
Requires-Dist: sphinx==9.1.0; extra == "dev"
Requires-Dist: alabaster==1.0.0; extra == "dev"
Requires-Dist: pillow==12.1.0; extra == "dev"
Requires-Dist: flake8==7.3.0; extra == "dev"
Requires-Dist: pytest-cov==7.0.0; extra == "dev"
Dynamic: author
Dynamic: author-email
Dynamic: classifier
Dynamic: description
Dynamic: home-page
Dynamic: keywords
Dynamic: license
Dynamic: maintainer
Dynamic: maintainer-email
Dynamic: provides-extra
Dynamic: requires-dist
Dynamic: requires-python
Dynamic: summary
